[
  {
    "id": 1,
    "date": "2024/03/25",
    "write": " 똘이",
    "category": "best",
    "like": 2324,
    "heart": "../img/KakaoTalk_20240325_160943153.png",
    "name": "우리 반려동물의 귀여운 일상 ",
    "picture": "../img/communityImg/생일파티.jpg",
    "comment": "우리 반려동물들이 하는 귀여운 행동이나 재미있는 이야기를 함께 공유해보아요! 사랑스러운 사진과 함께 더욱 특별한 순간을 기록해보세요."
  },
  {
    "id": 2,
    "date": "2024/03/25",
    "write": "건강이 짱이다",
    "category": "free",
    "like": 154,
    "heart": "../img/KakaoTalk_20240325_160943153.png",
    "name": "반려동물을 위한 건강한 식습관에 대해 알아봐요!",
    "picture": "../img/communityImg/간식.png",
    "comment": "우리 반려동물의 건강을 위해 중요한 식습관과 영양소에 대해 함께 공유해봐요! 맛있고 건강한 레시피나 영양 꿀팁이 있다면 함께 공유해주세요."
  },
  {
    "id": 3,
    "date": "2024/03/25",
    "write": "여행자",
    "category": "review",
    "like": 293,
    "heart": "../img/KakaoTalk_20240325_160943153.png",
    "name": "반려동물과의 특별한 여행 이야기",
    "picture": "../img/communityImg/여행.png",
    "comment": "반려동물과 함께 다녀온 여행 이야기를 공유해보아요! 함께 다녀온 장소나 특별한 경험을 나누고 여행 팁을 함께 나눠보아요."
  },
  {
    "id": 4,
    "date": "2024/03/25",
    "write": "궁금증",
    "category": "question",
    "like": 1234,
    "heart": "../img/KakaoTalk_20240325_160943153.png",
    "name": "반려동물의 취향은? ",
    "picture": "../img/communityImg/갸우뚱.png",
    "comment": "asdfasdf"
  },
  {
    "id": 5,
    "date": "2024/03/25",
    "write": "힐링이 필요해",
    "category": "free",
    "like": 615,
    "heart": "../img/KakaoTalk_20240325_160943153.png",
    "name": "반려동물과 함께하는 힐링 타임",
    "picture": "../img/communityImg/힐링.png",
    "comment": "반려동물과 함께하는 힐링 타임을 공유해보아요! 함께하는 시간을 통해 스트레스 해소와 힐링을 얻는 다양한 방법을 나눠봐요."
  },
  {
    "id": 6,
    "date": "2024/03/25",
    "write": "나그네",
    "category": "free",
    "like": 463,
    "heart": "../img/KakaoTalk_20240325_160943153.png",
    "name": "반려동물과 함께하는 가을 산책코스 추천",
    "picture": "../img/communityImg/나그네.png",
    "comment": "가을이면 함께 즐길 수 있는 반려동물과의 산책코스를 추천해주세요! 함께하는 시간을 특별하게 만들어줄 자연 속의 아름다운 경로를 공유해봐요."
  },
  {
    "id": 7,
    "date": "2024/03/25",
    "write": "블루클럽",
    "category": "review",
    "like": 1004,
    "heart": "../img/KakaoTalk_20240325_160943153.png",
    "name": "동물병원에서 건강한 미용과 관리에 대해 알아요",
    "picture": "../img/communityImg/미용.png",
    "comment": "우리 반려동물의 털 관리, 목욕, 발톱 깎기 등 건강한 미용과 관리에 대해 친절해요! 미용에 필요한 도구나 꿀팁도 공유해줘요."
  },
  {
    "id": 8,
    "date": "2024/03/25",
    "write": "떠나",
    "category": "review",
    "like": 486,
    "heart": "../img/KakaoTalk_20240325_160943153.png",
    "name": "반려동물과 함께하는 여름 휴가",
    "picture": "../img/communityImg/떠나.png",
    "comment": "asdfasdf"
  },
  {
    "id": 9,
    "date": "2024/03/25",
    "write": "아웃사이더",
    "categoty": "question",
    "like": 100,
    "heart": "../img/KakaoTalk_20240325_160943153.png",
    "name": "반려동물과 함께하는 가을 야외 데이트 스팟",
    "picture": "../img/communityImg/외향적.png",
    "comment": "가을 특유의 아름다운 풍경과 함께하는 반려동물과의 야외 데이트 스팟을 소개해주세요!"
  },
  {
    "id": 10,
    "date": "2024/03/25",
    "write": "인사이더",
    "categoty": "question",
    "like": 992,
    "heart": "../img/KakaoTalk_20240325_160943153.png",
    "name": "반려동물과 함께하는 실내 활동 아이디어",
    "picture": "../img/communityImg/내향적.png",
    "comment": "실내에서도 함께 할 수 있는 반려동물과의 재미있는 활동이나 놀이 아이디어를 공유해주세요!"
  },
  {
    "id": 11,
    "date": "2024/03/25",
    "write": "파티",
    "categoty": "review",
    "like": 580,
    "heart": "../img/KakaoTalk_20240325_160943153.png",
    "name": "반려동물과 함께하는 홈파티 아이디어",
    "picture": "../img/communityImg/파티.png",
    "comment": "집에서 반려동물과 함께하는 특별한 홈파티를 계획해보아요! 함께하는 파티 게임, 간식, 장식 아이디어를 공유하고 즐거운 시간을 보내봐요."
  },
  {
    "id": 12,
    "date": "2024/03/25",
    "write": "루미펫",
    "categoty": "free",
    "like": 119,
    "heart": "../img/KakaoTalk_20240325_160943153.png",
    "name": "반려동물과 함께하는 자유로운 야외 활동의 중요성",
    "picture": "../img/communityImg/야외활동.png",
    "comment": "반려동물과 함께하는 자유로운 야외 활동이 얼마나 중요한지에 대해 이야기해봐요! 함께하는 활동을 통해 우리의 동반자들이 행복하고 건강하게 자라나는 것을 지켜보아요."
  },
  {
    "id": 13,
    "date": "2024/03/25",
    "write": "포토북",
    "categoty": "best",
    "like": 356,
    "heart": "../img/KakaoTalk_20240325_160943153.png",
    "name": "반려동물과의 특별한 순간을 담은 포토북 만들기",
    "picture": "../img/communityImg/포토북.png",
    "comment": "우리 반려동물과의 소중한 순간을 담은 포토북을 만들어보아요! 함께한 추억을 간직할 수 있는 포토북을 만들면서 반려동물과의 특별한 연결을 느껴봐요."
  },
  {
    "id": 14,
    "date": "2024/03/25",
    "write": "꿀팁",
    "categoty": "best",
    "like": 290,
    "heart": "../img/KakaoTalk_20240325_160943153.png",
    "name": "반려동물의 건강을 위한 자가진단과 케어 팁",
    "picture": "../img/communityImg/꿀팁.png",
    "comment": "우리 반려동물들의 건강을 위해 자가진단을 할 수 있는 방법과 케어 팁을 나눠보아요! 일상적인 건강 관리를 통해 우리의 동반자들이 건강하게 지내도록 도와봐요."
  },
  {
    "id": 15,
    "date": "2024/03/25",
    "write": "애견카페",
    "categoty": "question",
    "like": 777,
    "heart": "../img/KakaoTalk_20240325_160943153.png",
    "name": "반려동물과 함께하는 애견 카페 추천",
    "picture": "../img/communityImg/애견카페.png",
    "comment": "애견 카페를 돌며 함께하는 특별한 시간을 보내고싶어요! 어디가 좋을지 추천해주세요."
  },
  {
    "id": 16,
    "date": "2024/03/25",
    "write": "컬쳐랜드",
    "categoty": "best",
    "like": 152,
    "heart": "../img/KakaoTalk_20240325_160943153.png",
    "name": "반려동물과 함께하는 문화생활",
    "picture": "../img/communityImg/컬쳐랜드.png",
    "comment": "미술관이나 박물관 등 문화 시설을 함께하는 특별한 시간을 보내보아요! 문화 생활을 통해 함께 성장하고 즐거운 경험을 나누어봐요."
  }
]
